simplecharts.py
simplecharts-0.1.1.dist-info/licenses/LICENSE
simplecharts-0.1.1.dist-info/METADATA
simplecharts-0.1.1.dist-info/WHEEL
simplecharts-0.1.1.dist-info/entry_points.txt
simplecharts-0.1.1.dist-info/top_level.txt
simplecharts-0.1.1.dist-info/RECORD
