Metadata-Version: 2.4
Name: simplecharts
Version: 0.1.1
Summary: SVG charts without dependencies
Author-email: Tobias Bengfort <tobias.bengfort@posteo.de>
License: MIT
Project-URL: Homepage, https://github.com/xi/simplecharts
Keywords: svg,charts
Classifier: Topic :: Scientific/Engineering :: Visualization
License-File: LICENSE
Dynamic: license-file
